Workbook

Sheet Summary
A1: Big Jo's Beds: 12-month bootstrap cashflow plan
A2: Side hustle with no salary. Customers pay upfront and PBS builds to order in 3-5 days, so there is no stock to fund: the cash need is launch costs plus marketing until sales cover them.
A3: Plan runs Oct 2026 to Sep 2027. Change the blue inputs on the Assumptions sheet; everything here recalculates.
A5: Metric | B5: Slow | C5: Base | D5: Target
A6: Sets sold | B6: ='Slow case'!B6 -> 23 | C6: ='Base case'!B6 -> 57 | D6: ='Target case'!B6 -> 122
A7: Sales (bed sets and bedding) | B7: ='Slow case'!B10+'Slow case'!B11 -> 585320.1 | C7: ='Base case'!B10+'Base case'!B11 -> 1450575.9 | D7: ='Target case'!B10+'Target case'!B11 -> 3104741.4
A8: Refunds on returns | B8: ='Slow case'!B12 -> -8999.64 | C8: ='Base case'!B12 -> -22499.1 | D8: ='Target case'!B12 -> -49498.02
A9: Gross contribution | B9: ='Slow case'!B27 -> 319002.26 | C9: ='Base case'!B27 -> 790371.64 | D9: ='Target case'!B27 -> 1690306.4
A10: Gross contribution per set | B10: =IF('Slow case'!B6>0,'Slow case'!B27/'Slow case'!B6,0) -> 13869.663 | C10: =IF('Base case'!B6>0,'Base case'!B27/'Base case'!B6,0) -> 13866.169 | D10: =IF('Target case'!B6>0,'Target case'!B27/'Target case'!B6,0) -> 13854.971
A11: Marketing | B11: ='Slow case'!B30 -> -108000 | C11: ='Base case'!B30 -> -108000 | D11: ='Target case'!B30 -> -108000
A12: Marketing per set sold | B12: =IF('Slow case'!B6>0,-'Slow case'!B30/'Slow case'!B6,0) -> 4695.6522 | C12: =IF('Base case'!B6>0,-'Base case'!B30/'Base case'!B6,0) -> 1894.7368 | D12: =IF('Target case'!B6>0,-'Target case'!B30/'Target case'!B6,0) -> 885.2459
A13: Fixed running costs | B13: ='Slow case'!B31 -> -24500 | C13: ='Base case'!B31 -> -24500 | D13: ='Target case'!B31 -> -24500
A14: One-off launch costs | B14: ='Slow case'!B32 -> -20380 | C14: ='Base case'!B32 -> -20380 | D14: ='Target case'!B32 -> -20380
A15: VAT paid to SARS | B15: ='Slow case'!B33 -> 0 | C15: ='Base case'!B33 -> 0 | D15: ='Target case'!B33 -> -38702.863
A16: Net cash generated in 12 months | B16: ='Slow case'!B36 -> 166122.26 | C16: ='Base case'!B36 -> 637491.64 | D16: ='Target case'!B36 -> 1498723.6
A17: Peak founder cash needed | B17: =MAX(0,-MIN('Slow case'!C42:N42)) -> 29262.004 | C17: =MAX(0,-MIN('Base case'!C42:N42)) -> 12112.004 | D17: =MAX(0,-MIN('Target case'!C42:N42)) -> 11230
A18: Lowest cash balance (after your injection) | B18: =MIN('Slow case'!C39:N39) -> 10737.996 | C18: =MIN('Base case'!C39:N39) -> 27887.996 | D18: =MIN('Target case'!C39:N39) -> 28770
A19: Cash in the bank, Sep 2027 | B19: ='Slow case'!N39 -> 206122.26 | C19: ='Base case'!N39 -> 677491.64 | D19: ='Target case'!N39 -> 1538723.6
A20: Cumulative cash turns positive in | B20: =IFERROR(INDEX('Slow case'!C5:N5,MATCH(1,'Slow case'!C45:N45,0)),"Not in 12 months") -> Apr 2027 | C20: =IFERROR(INDEX('Base case'!C5:N5,MATCH(1,'Base case'!C45:N45,0)),"Not in 12 months") -> Jan 2027 | D20: =IFERROR(INDEX('Target case'!C5:N5,MATCH(1,'Target case'!C45:N45,0)),"Not in 12 months") -> Nov 2026
A21: VAT registration needed from | B21: =IF('Slow case'!B46<=12,INDEX('Slow case'!C5:N5,'Slow case'!B46),"Not in 12 months") -> Not in 12 months | C21: =IF('Base case'!B46<=12,INDEX('Base case'!C5:N5,'Base case'!B46),"Not in 12 months") -> Not in 12 months | D21: =IF('Target case'!B46<=12,INDEX('Target case'!C5:N5,'Target case'!B46),"Not in 12 months") -> Sep 2027
A23: Sets a month needed to cover full-rate marketing and fixed costs | B23: =(Assumptions!N64+Assumptions!B44)/Assumptions!B25 -> 0.8996984 | C23: Uses Sep 2027 marketing and the contribution per set on the Assumptions sheet
A25: Cash in the bank at month end
A26: Month | B26: =Assumptions!C63 -> Oct 2026 | C26: =Assumptions!D63 -> Nov 2026 | D26: =Assumptions!E63 -> Dec 2026 | E26: =Assumptions!F63 -> Jan 2027 | F26: =Assumptions!G63 -> Feb 2027 | G26: =Assumptions!H63 -> Mar 2027 | H26: =Assumptions!I63 -> Apr 2027 | I26: =Assumptions!J63 -> May 2027 | ... M26: =Assumptions!N63 -> Sep 2027
A27: Slow | B27: ='Slow case'!C39 -> 28770 | C27: ='Slow case'!D39 -> 13620 | D27: ='Slow case'!E39 -> 10737.996 | E27: ='Slow case'!F39 -> 12855.991 | F27: ='Slow case'!G39 -> 14973.987 | G27: ='Slow case'!H39 -> 30596.507 | H27: ='Slow case'!I39 -> 46219.029 | I27: ='Slow case'!J39 -> 61841.55 | ... M27: ='Slow case'!N39 -> 206122.26
A28: Base | B28: ='Base case'!C39 -> 28770 | C28: ='Base case'!D39 -> 27887.996 | D28: ='Base case'!E39 -> 39273.986 | E28: ='Base case'!F39 -> 55659.978 | F28: ='Base case'!G39 -> 85550.494 | G28: ='Base case'!H39 -> 128945.54 | H28: ='Base case'!I39 -> 186608.57 | I28: ='Base case'!J39 -> 257776.14 | ... M28: ='Base case'!N39 -> 677491.64
A29: Target | B29: ='Target case'!C39 -> 28770 | C29: ='Target case'!D39 -> 42155.991 | D29: ='Target case'!E39 -> 82077.973 | E29: ='Target case'!F39 -> 141267.95 | F29: ='Target case'!G39 -> 227466.98 | G29: ='Target case'!H39 -> 340675.06 | H29: ='Target case'!I39 -> 481655.66 | I29: ='Target case'!J39 -> 649645.31 | ... M29: ='Target case'!N39 -> 1538723.6

Sheet Assumptions
A1: Big Jo's Beds: assumptions
A2: Blue = input you can change. Yellow fill = key assumption. Black = formula. All rand amounts include VAT.
A4: Pricing
A5: Launch price per set (mattress + base) | B5: 24999 | C5: Recommended launch price: reports/Big Jos Beds pricing and competition.md
A6: Step-up price per set | B6: 27999 | C6: Report: step up once the 250 kg test and ~50 reviews are in
A7: Step-up from month # | B7: 13 | C7: 13 = no step-up inside this plan. Set 1-12 to test it.
A8: Bedding add-on: share of buyers | B8: 0.3 | C8: Estimate: buyers who also buy an extra sheet set
A9: Bedding add-on price | B9: 1499 | C9: Estimate
A10: Bedding add-on cost | B10: 700 | C10: Estimate. Custom sheets are quote-only (Falucca, Bedworld, Linen and Co)
A12: Cost per set
A13: PBS mattress, 160 x 210 | B13: 5980 | C13: PBS quote QUO0010447, 6 Oct 2026 (single unit)
A14: PBS heavy-duty base, 160 x 210 | B14: 1950 | C14: PBS quote QUO0010447, 6 Oct 2026 (single unit)
A15: Volume discount from PBS | B15: 0 | C15: Not quoted yet. Ask Gary for 10 and 20 sets a month
A16: Delivery and white-glove setup | B16: 450 | C16: PBS lists R450 delivery within 55 km
A17: Old-bed removal and disposal | B17: 300 | C17: Estimate
A18: Custom bedding in the box (fitted sheet + protector) | B18: 1000 | C18: Estimate. Get quotes for 160 x 210 x ~28 cm
A19: Packaging, spec and warranty card | B19: 150 | C19: Estimate
A20: Payment fees (card and pay-later), % of receipts | B20: 0.035 | C20: Estimate: blended card and PayJustNow/Payflex fees
A21: Warranty reserve per set (set aside) | B21: 250 | C21: Estimate. Treated as cash set aside, not spent
A22: Return rate (100-night trial) | B22: 0.03 | C22: Sloom reports returns under 3%. Returned custom sets assumed unsellable
A23: Refund paid this many months after the sale | B23: 3 | C23: About 100 nights
A24: Collection cost per return | B24: 450 | C24: Assumed equal to delivery
A25: Cash contribution per set, before marketing and overheads | B25: =B5*(1-B20)-(B13+B14)*(1-B15)-B16-B17-B18-B19-B21-B22*(B5+B24)+B8*(B9*(1-B20)-B10) -> 13504.525 | C25: At launch price, before VAT registration, including the expected cost of returns and add-ons
A27: VAT
A28: VAT rate | B28: 0.15 | C28: SARS
A29: Compulsory registration threshold (12-month sales) | B29: 2300000 | C29: SARS: R2.3m from 1 Apr 2026, sars.gov.za/faq/what-is-the-new-threshold-for-vat-registration/
A30: Register voluntarily from month # | B30: 13 | C30: 13 = only register when the threshold forces it
A32: Founder funding
A33: Founder cash injection | B33: 40000 | C33: Your own cash. Check "Peak founder cash needed" on the Summary sheet
A34: Injection in month # | B34: 1
A36: Fixed monthly costs
A37: Item | B37: Rand / month | C37: Starts month # | D37: Note
A38: Shopify plan and apps | B38: 800 | C38: 2 | D38: Estimate (about USD 29 plan plus apps)
A39: Domain and email | B39: 150 | C39: 1 | D39: Estimate
A40: Bookkeeping software | B40: 400 | C40: 1 | D40: Estimate
A41: Product and public liability insurance | B41: 500 | C41: 2 | D41: Estimate. Get a quote
A42: Phone, WhatsApp Business and admin | B42: 300 | C42: 1 | D42: Estimate
A43: Founder salary | B43: 0 | C43: 1 | D43: Side hustle: no salary in year 1
A44: Total when all running | B44: =SUM(B38:B43) -> 2150
A46: One-off launch costs
A47: Item | B47: Rand | C47: Month # | D47: Note
A48: Demo and photo unit (first PBS order) | B48: 7930 | C48: 1 | D48: PBS quote QUO0010447
A49: Demo unit delivery | B49: 450 | C49: 1 | D49: PBS lists R450
A50: Company registration and bank account | B50: 500 | C50: 1 | D50: Estimate (CIPC)
A51: Trademark filing, classes 20 and 24 | B51: 1500 | C51: 1 | D51: Estimate, filing yourself via CIPC
A52: Brand identity and label design | B52: 0 | C52: 1 | D52: DIY. A freelance designer was estimated at R20,000
A53: Website build | B53: 0 | C53: 2 | D53: DIY on Shopify. The Shopify plan is still in fixed costs. Was R10,000
A54: Photo and video shoot | B54: 0 | C54: 2 | D54: DIY. Was R8,000
A55: Branded side-panel label setup | B55: 3000 | C55: 2 | D55: Estimate. Ask PBS
A56: Custom bedding samples | B56: 2000 | C56: 2 | D56: Estimate
A57: Launch activation (e.g. a Get Lucky golf day stand) | B57: 5000 | C57: 3 | D57: Estimate
A58: 250 kg durability test | B58: 0 | C58: 4 | D58: DIY, so not independent proof. An SABS or university lab test was estimated at R25,000
A59: Total | B59: =SUM(B48:B58) -> 20380
A61: Monthly inputs
A62: Month # | B62: Total | C62: 1 | D62: 2 | E62: 3 | F62: 4 | G62: 5 | H62: 6 | I62: 7 | J62: 8 | K62: 9 | L62: 10 | M62: 11 | N62: 12
A63: Month | C63: Oct 2026 | D63: Nov 2026 | E63: Dec 2026 | F63: Jan 2027 | G63: Feb 2027 | H63: Mar 2027 | I63: Apr 2027 | J63: May 2027 | K63: Jun 2027 | L63: Jul 2027 | M63: Aug 2027 | N63: Sep 2027
A64: Marketing spend (R) | B64: =SUM(C64:N64) -> 108000 | C64: 0 | D64: 8000 | E64: 10000 | F64: 10000 | G64: 10000 | H64: 10000 | I64: 10000 | J64: 10000 | K64: 10000 | L64: 10000 | M64: 10000 | N64: 10000
A66: Sets sold per month
A67: 1. Slow | B67: =SUM(C67:N67) -> 23 | C67: 0 | D67: 0 | E67: 1 | F67: 1 | G67: 1 | H67: 2 | I67: 2 | J67: 2 | K67: 3 | L67: 3 | M67: 4 | N67: 4
A68: 2. Base | B68: =SUM(C68:N68) -> 57 | C68: 0 | D68: 1 | E68: 2 | F68: 2 | G68: 3 | H68: 4 | I68: 5 | J68: 6 | K68: 7 | L68: 8 | M68: 9 | N68: 10
A69: 3. Target | B69: =SUM(C69:N69) -> 122 | C69: 0 | D69: 2 | E69: 4 | F69: 5 | G69: 7 | H69: 9 | I69: 11 | J69: 13 | K69: 15 | L69: 17 | M69: 19 | N69: 20
A71: Sales start in Nov 2026 once the demo unit is photographed. Marketing is the same in every scenario, so the Slow case shows the downside of spending the same and selling less.

Sheet Slow case
A1: Big Jo's Beds: 12-month cashflow, slow case
A2: Scenario # (1 Slow, 2 Base, 3 Target) | B2: 1 | C2: All figures in rand incl. VAT. Inflows positive, outflows in brackets.
A4: Month # | C4: =Assumptions!C62 -> 1 | D4: =Assumptions!D62 -> 2 | E4: =Assumptions!E62 -> 3 | F4: =Assumptions!F62 -> 4 | G4: =Assumptions!G62 -> 5 | H4: =Assumptions!H62 -> 6 | I4: =Assumptions!I62 -> 7 | J4: =Assumptions!J62 -> 8 | ... N4: =Assumptions!N62 -> 12
A5: Month | B5: 12 months | C5: =Assumptions!C63 -> Oct 2026 | D5: =Assumptions!D63 -> Nov 2026 | E5: =Assumptions!E63 -> Dec 2026 | F5: =Assumptions!F63 -> Jan 2027 | G5: =Assumptions!G63 -> Feb 2027 | H5: =Assumptions!H63 -> Mar 2027 | I5: =Assumptions!I63 -> Apr 2027 | J5: =Assumptions!J63 -> May 2027 | ... N5: =Assumptions!N63 -> Sep 2027
A6: Sets sold | B6: =SUM(C6:N6) -> 23 | C6: =INDEX(Assumptions!$C$67:$N$69,$B$2,C$4) -> 0 | D6: =INDEX(Assumptions!$C$67:$N$69,$B$2,D$4) -> 0 | E6: =INDEX(Assumptions!$C$67:$N$69,$B$2,E$4) -> 1 | F6: =INDEX(Assumptions!$C$67:$N$69,$B$2,F$4) -> 1 | G6: =INDEX(Assumptions!$C$67:$N$69,$B$2,G$4) -> 1 | H6: =INDEX(Assumptions!$C$67:$N$69,$B$2,H$4) -> 2 | I6: =INDEX(Assumptions!$C$67:$N$69,$B$2,I$4) -> 2 | J6: =INDEX(Assumptions!$C$67:$N$69,$B$2,J$4) -> 2 | ... N6: =INDEX(Assumptions!$C$67:$N$69,$B$2,N$4) -> 4
A7: Price per set | C7: =IF(C$4>=Assumptions!$B$7,Assumptions!$B$6,Assumptions!$B$5) -> 24999 | D7: =IF(D$4>=Assumptions!$B$7,Assumptions!$B$6,Assumptions!$B$5) -> 24999 | E7: =IF(E$4>=Assumptions!$B$7,Assumptions!$B$6,Assumptions!$B$5) -> 24999 | F7: =IF(F$4>=Assumptions!$B$7,Assumptions!$B$6,Assumptions!$B$5) -> 24999 | G7: =IF(G$4>=Assumptions!$B$7,Assumptions!$B$6,Assumptions!$B$5) -> 24999 | H7: =IF(H$4>=Assumptions!$B$7,Assumptions!$B$6,Assumptions!$B$5) -> 24999 | I7: =IF(I$4>=Assumptions!$B$7,Assumptions!$B$6,Assumptions!$B$5) -> 24999 | J7: =IF(J$4>=Assumptions!$B$7,Assumptions!$B$6,Assumptions!$B$5) -> 24999 | ... N7: =IF(N$4>=Assumptions!$B$7,Assumptions!$B$6,Assumptions!$B$5) -> 24999
A9: Cash in
A10: Bed set sales | B10: =SUM(C10:N10) -> 574977 | C10: =C6*C7 -> 0 | D10: =D6*D7 -> 0 | E10: =E6*E7 -> 24999 | F10: =F6*F7 -> 24999 | G10: =G6*G7 -> 24999 | H10: =H6*H7 -> 49998 | I10: =I6*I7 -> 49998 | J10: =J6*J7 -> 49998 | ... N10: =N6*N7 -> 99996
A11: Bedding add-ons | B11: =SUM(C11:N11) -> 10343.1 | C11: =C6*Assumptions!$B$8*Assumptions!$B$9 -> 0 | D11: =D6*Assumptions!$B$8*Assumptions!$B$9 -> 0 | E11: =E6*Assumptions!$B$8*Assumptions!$B$9 -> 449.7 | F11: =F6*Assumptions!$B$8*Assumptions!$B$9 -> 449.7 | G11: =G6*Assumptions!$B$8*Assumptions!$B$9 -> 449.7 | H11: =H6*Assumptions!$B$8*Assumptions!$B$9 -> 899.4 | I11: =I6*Assumptions!$B$8*Assumptions!$B$9 -> 899.4 | J11: =J6*Assumptions!$B$8*Assumptions!$B$9 -> 899.4 | ... N11: =N6*Assumptions!$B$8*Assumptions!$B$9 -> 1798.8
A12: Refunds on returns | B12: =SUM(C12:N12) -> -8999.64 | C12: =IF(C$4>Assumptions!$B$23,-OFFSET(C10,0,-Assumptions!$B$23)*Assumptions!$B$22,0) -> 0 | D12: =IF(D$4>Assumptions!$B$23,-OFFSET(D10,0,-Assumptions!$B$23)*Assumptions!$B$22,0) -> 0 | E12: =IF(E$4>Assumptions!$B$23,-OFFSET(E10,0,-Assumptions!$B$23)*Assumptions!$B$22,0) -> 0 | F12: =IF(F$4>Assumptions!$B$23,-OFFSET(F10,0,-Assumptions!$B$23)*Assumptions!$B$22,0) -> 0 | G12: =IF(G$4>Assumptions!$B$23,-OFFSET(G10,0,-Assumptions!$B$23)*Assumptions!$B$22,0) -> 0 | H12: =IF(H$4>Assumptions!$B$23,-OFFSET(H10,0,-Assumptions!$B$23)*Assumptions!$B$22,0) -> -749.97 | I12: =IF(I$4>Assumptions!$B$23,-OFFSET(I10,0,-Assumptions!$B$23)*Assumptions!$B$22,0) -> -749.97 | J12: =IF(J$4>Assumptions!$B$23,-OFFSET(J10,0,-Assumptions!$B$23)*Assumptions!$B$22,0) -> -749.97 | ... N12: =IF(N$4>Assumptions!$B$23,-OFFSET(N10,0,-Assumptions!$B$23)*Assumptions!$B$22,0) -> -2249.91
A13: Total cash in | B13: =SUM(C13:N13) -> 576320.46 | C13: =SUM(C10:C12) -> 0 | D13: =SUM(D10:D12) -> 0 | E13: =SUM(E10:E12) -> 25448.7 | F13: =SUM(F10:F12) -> 25448.7 | G13: =SUM(G10:G12) -> 25448.7 | H13: =SUM(H10:H12) -> 50147.43 | I13: =SUM(I10:I12) -> 50147.43 | J13: =SUM(J10:J12) -> 50147.43 | ... N13: =SUM(N10:N12) -> 99544.89
A15: Cost of each sale
A16: PBS mattress and base | B16: =SUM(C16:N16) -> -182390 | C16: =-C6*(Assumptions!$B$13+Assumptions!$B$14)*(1-Assumptions!$B$15) -> 0 | D16: =-D6*(Assumptions!$B$13+Assumptions!$B$14)*(1-Assumptions!$B$15) -> 0 | E16: =-E6*(Assumptions!$B$13+Assumptions!$B$14)*(1-Assumptions!$B$15) -> -7930 | F16: =-F6*(Assumptions!$B$13+Assumptions!$B$14)*(1-Assumptions!$B$15) -> -7930 | G16: =-G6*(Assumptions!$B$13+Assumptions!$B$14)*(1-Assumptions!$B$15) -> -7930 | H16: =-H6*(Assumptions!$B$13+Assumptions!$B$14)*(1-Assumptions!$B$15) -> -15860 | I16: =-I6*(Assumptions!$B$13+Assumptions!$B$14)*(1-Assumptions!$B$15) -> -15860 | J16: =-J6*(Assumptions!$B$13+Assumptions!$B$14)*(1-Assumptions!$B$15) -> -15860 | ... N16: =-N6*(Assumptions!$B$13+Assumptions!$B$14)*(1-Assumptions!$B$15) -> -31720
A17: Delivery and setup | B17: =SUM(C17:N17) -> -10350 | C17: =-C6*Assumptions!$B$16 -> 0 | D17: =-D6*Assumptions!$B$16 -> 0 | E17: =-E6*Assumptions!$B$16 -> -450 | F17: =-F6*Assumptions!$B$16 -> -450 | G17: =-G6*Assumptions!$B$16 -> -450 | H17: =-H6*Assumptions!$B$16 -> -900 | I17: =-I6*Assumptions!$B$16 -> -900 | J17: =-J6*Assumptions!$B$16 -> -900 | ... N17: =-N6*Assumptions!$B$16 -> -1800
A18: Old-bed removal | B18: =SUM(C18:N18) -> -6900 | C18: =-C6*Assumptions!$B$17 -> 0 | D18: =-D6*Assumptions!$B$17 -> 0 | E18: =-E6*Assumptions!$B$17 -> -300 | F18: =-F6*Assumptions!$B$17 -> -300 | G18: =-G6*Assumptions!$B$17 -> -300 | H18: =-H6*Assumptions!$B$17 -> -600 | I18: =-I6*Assumptions!$B$17 -> -600 | J18: =-J6*Assumptions!$B$17 -> -600 | ... N18: =-N6*Assumptions!$B$17 -> -1200
A19: Bedding in the box | B19: =SUM(C19:N19) -> -23000 | C19: =-C6*Assumptions!$B$18 -> 0 | D19: =-D6*Assumptions!$B$18 -> 0 | E19: =-E6*Assumptions!$B$18 -> -1000 | F19: =-F6*Assumptions!$B$18 -> -1000 | G19: =-G6*Assumptions!$B$18 -> -1000 | H19: =-H6*Assumptions!$B$18 -> -2000 | I19: =-I6*Assumptions!$B$18 -> -2000 | J19: =-J6*Assumptions!$B$18 -> -2000 | ... N19: =-N6*Assumptions!$B$18 -> -4000
A20: Packaging and cards | B20: =SUM(C20:N20) -> -3450 | C20: =-C6*Assumptions!$B$19 -> 0 | D20: =-D6*Assumptions!$B$19 -> 0 | E20: =-E6*Assumptions!$B$19 -> -150 | F20: =-F6*Assumptions!$B$19 -> -150 | G20: =-G6*Assumptions!$B$19 -> -150 | H20: =-H6*Assumptions!$B$19 -> -300 | I20: =-I6*Assumptions!$B$19 -> -300 | J20: =-J6*Assumptions!$B$19 -> -300 | ... N20: =-N6*Assumptions!$B$19 -> -600
A21: Bedding add-on cost | B21: =SUM(C21:N21) -> -4830 | C21: =-C6*Assumptions!$B$8*Assumptions!$B$10 -> 0 | D21: =-D6*Assumptions!$B$8*Assumptions!$B$10 -> 0 | E21: =-E6*Assumptions!$B$8*Assumptions!$B$10 -> -210 | F21: =-F6*Assumptions!$B$8*Assumptions!$B$10 -> -210 | G21: =-G6*Assumptions!$B$8*Assumptions!$B$10 -> -210 | H21: =-H6*Assumptions!$B$8*Assumptions!$B$10 -> -420 | I21: =-I6*Assumptions!$B$8*Assumptions!$B$10 -> -420 | J21: =-J6*Assumptions!$B$8*Assumptions!$B$10 -> -420 | ... N21: =-N6*Assumptions!$B$8*Assumptions!$B$10 -> -840
A22: Collecting returned sets | B22: =SUM(C22:N22) -> -162 | C22: =IF(C$4>Assumptions!$B$23,-OFFSET(C6,0,-Assumptions!$B$23)*Assumptions!$B$22*Assumptions!$B$24,0) -> 0 | D22: =IF(D$4>Assumptions!$B$23,-OFFSET(D6,0,-Assumptions!$B$23)*Assumptions!$B$22*Assumptions!$B$24,0) -> 0 | E22: =IF(E$4>Assumptions!$B$23,-OFFSET(E6,0,-Assumptions!$B$23)*Assumptions!$B$22*Assumptions!$B$24,0) -> 0 | F22: =IF(F$4>Assumptions!$B$23,-OFFSET(F6,0,-Assumptions!$B$23)*Assumptions!$B$22*Assumptions!$B$24,0) -> 0 | G22: =IF(G$4>Assumptions!$B$23,-OFFSET(G6,0,-Assumptions!$B$23)*Assumptions!$B$22*Assumptions!$B$24,0) -> 0 | H22: =IF(H$4>Assumptions!$B$23,-OFFSET(H6,0,-Assumptions!$B$23)*Assumptions!$B$22*Assumptions!$B$24,0) -> -13.5 | I22: =IF(I$4>Assumptions!$B$23,-OFFSET(I6,0,-Assumptions!$B$23)*Assumptions!$B$22*Assumptions!$B$24,0) -> -13.5 | J22: =IF(J$4>Assumptions!$B$23,-OFFSET(J6,0,-Assumptions!$B$23)*Assumptions!$B$22*Assumptions!$B$24,0) -> -13.5 | ... N22: =IF(N$4>Assumptions!$B$23,-OFFSET(N6,0,-Assumptions!$B$23)*Assumptions!$B$22*Assumptions!$B$24,0) -> -40.5
A23: Payment fees | B23: =SUM(C23:N23) -> -20486.203 | C23: =-(C10+C11)*Assumptions!$B$20 -> 0 | D23: =-(D10+D11)*Assumptions!$B$20 -> 0 | E23: =-(E10+E11)*Assumptions!$B$20 -> -890.7045 | F23: =-(F10+F11)*Assumptions!$B$20 -> -890.7045 | G23: =-(G10+G11)*Assumptions!$B$20 -> -890.7045 | H23: =-(H10+H11)*Assumptions!$B$20 -> -1781.409 | I23: =-(I10+I11)*Assumptions!$B$20 -> -1781.409 | J23: =-(J10+J11)*Assumptions!$B$20 -> -1781.409 | ... N23: =-(N10+N11)*Assumptions!$B$20 -> -3562.818
A24: Warranty reserve (set aside) | B24: =SUM(C24:N24) -> -5750 | C24: =-C6*Assumptions!$B$21 -> 0 | D24: =-D6*Assumptions!$B$21 -> 0 | E24: =-E6*Assumptions!$B$21 -> -250 | F24: =-F6*Assumptions!$B$21 -> -250 | G24: =-G6*Assumptions!$B$21 -> -250 | H24: =-H6*Assumptions!$B$21 -> -500 | I24: =-I6*Assumptions!$B$21 -> -500 | J24: =-J6*Assumptions!$B$21 -> -500 | ... N24: =-N6*Assumptions!$B$21 -> -1000
A25: Total cost of sales | B25: =SUM(C25:N25) -> -257318.2 | C25: =SUM(C16:C24) -> 0 | D25: =SUM(D16:D24) -> 0 | E25: =SUM(E16:E24) -> -11180.704 | F25: =SUM(F16:F24) -> -11180.704 | G25: =SUM(G16:G24) -> -11180.704 | H25: =SUM(H16:H24) -> -22374.909 | I25: =SUM(I16:I24) -> -22374.909 | J25: =SUM(J16:J24) -> -22374.909 | ... N25: =SUM(N16:N24) -> -44763.318
A27: Gross contribution | B27: =SUM(C27:N27) -> 319002.26 | C27: =C13+C25 -> 0 | D27: =D13+D25 -> 0 | E27: =E13+E25 -> 14267.996 | F27: =F13+F25 -> 14267.996 | G27: =G13+G25 -> 14267.996 | H27: =H13+H25 -> 27772.521 | I27: =I13+I25 -> 27772.521 | J27: =J13+J25 -> 27772.521 | ... N27: =N13+N25 -> 54781.572
A29: Overheads and launch
A30: Marketing | B30: =SUM(C30:N30) -> -108000 | C30: =-Assumptions!C64 -> 0 | D30: =-Assumptions!D64 -> -8000 | E30: =-Assumptions!E64 -> -10000 | F30: =-Assumptions!F64 -> -10000 | G30: =-Assumptions!G64 -> -10000 | H30: =-Assumptions!H64 -> -10000 | I30: =-Assumptions!I64 -> -10000 | J30: =-Assumptions!J64 -> -10000 | ... N30: =-Assumptions!N64 -> -10000
A31: Fixed running costs | B31: =SUM(C31:N31) -> -24500 | C31: =-SUMPRODUCT((Assumptions!$C$38:$C$43<=C$4)*Assumptions!$B$38:$B$43) -> -850 | D31: =-SUMPRODUCT((Assumptions!$C$38:$C$43<=D$4)*Assumptions!$B$38:$B$43) -> -2150 | E31: =-SUMPRODUCT((Assumptions!$C$38:$C$43<=E$4)*Assumptions!$B$38:$B$43) -> -2150 | F31: =-SUMPRODUCT((Assumptions!$C$38:$C$43<=F$4)*Assumptions!$B$38:$B$43) -> -2150 | G31: =-SUMPRODUCT((Assumptions!$C$38:$C$43<=G$4)*Assumptions!$B$38:$B$43) -> -2150 | H31: =-SUMPRODUCT((Assumptions!$C$38:$C$43<=H$4)*Assumptions!$B$38:$B$43) -> -2150 | I31: =-SUMPRODUCT((Assumptions!$C$38:$C$43<=I$4)*Assumptions!$B$38:$B$43) -> -2150 | J31: =-SUMPRODUCT((Assumptions!$C$38:$C$43<=J$4)*Assumptions!$B$38:$B$43) -> -2150 | ... N31: =-SUMPRODUCT((Assumptions!$C$38:$C$43<=N$4)*Assumptions!$B$38:$B$43) -> -2150
A32: One-off launch costs | B32: =SUM(C32:N32) -> -20380 | C32: =-SUMIF(Assumptions!$C$48:$C$58,C$4,Assumptions!$B$48:$B$58) -> -10380 | D32: =-SUMIF(Assumptions!$C$48:$C$58,D$4,Assumptions!$B$48:$B$58) -> -5000 | E32: =-SUMIF(Assumptions!$C$48:$C$58,E$4,Assumptions!$B$48:$B$58) -> -5000 | F32: =-SUMIF(Assumptions!$C$48:$C$58,F$4,Assumptions!$B$48:$B$58) -> 0 | G32: =-SUMIF(Assumptions!$C$48:$C$58,G$4,Assumptions!$B$48:$B$58) -> 0 | H32: =-SUMIF(Assumptions!$C$48:$C$58,H$4,Assumptions!$B$48:$B$58) -> 0 | I32: =-SUMIF(Assumptions!$C$48:$C$58,I$4,Assumptions!$B$48:$B$58) -> 0 | J32: =-SUMIF(Assumptions!$C$48:$C$58,J$4,Assumptions!$B$48:$B$58) -> 0 | ... N32: =-SUMIF(Assumptions!$C$48:$C$58,N$4,Assumptions!$B$48:$B$58) -> 0
A33: VAT paid to SARS (net) | B33: =SUM(C33:N33) -> 0 | C33: =IF(C$4>=$B$46,-(C13+SUM(C16:C22))*Assumptions!$B$28/(1+Assumptions!$B$28),0) -> 0 | D33: =IF(D$4>=$B$46,-(D13+SUM(D16:D22))*Assumptions!$B$28/(1+Assumptions!$B$28),0) -> 0 | E33: =IF(E$4>=$B$46,-(E13+SUM(E16:E22))*Assumptions!$B$28/(1+Assumptions!$B$28),0) -> 0 | F33: =IF(F$4>=$B$46,-(F13+SUM(F16:F22))*Assumptions!$B$28/(1+Assumptions!$B$28),0) -> 0 | G33: =IF(G$4>=$B$46,-(G13+SUM(G16:G22))*Assumptions!$B$28/(1+Assumptions!$B$28),0) -> 0 | H33: =IF(H$4>=$B$46,-(H13+SUM(H16:H22))*Assumptions!$B$28/(1+Assumptions!$B$28),0) -> 0 | I33: =IF(I$4>=$B$46,-(I13+SUM(I16:I22))*Assumptions!$B$28/(1+Assumptions!$B$28),0) -> 0 | J33: =IF(J$4>=$B$46,-(J13+SUM(J16:J22))*Assumptions!$B$28/(1+Assumptions!$B$28),0) -> 0 | ... N33: =IF(N$4>=$B$46,-(N13+SUM(N16:N22))*Assumptions!$B$28/(1+Assumptions!$B$28),0) -> 0
A34: Total overheads and launch | B34: =SUM(C34:N34) -> -152880 | C34: =SUM(C30:C33) -> -11230 | D34: =SUM(D30:D33) -> -15150 | E34: =SUM(E30:E33) -> -17150 | F34: =SUM(F30:F33) -> -12150 | G34: =SUM(G30:G33) -> -12150 | H34: =SUM(H30:H33) -> -12150 | I34: =SUM(I30:I33) -> -12150 | J34: =SUM(J30:J33) -> -12150 | ... N34: =SUM(N30:N33) -> -12150
A36: Net cash flow | B36: =SUM(C36:N36) -> 166122.26 | C36: =C27+C34 -> -11230 | D36: =D27+D34 -> -15150 | E36: =E27+E34 -> -2882.0045 | F36: =F27+F34 -> 2117.9955 | G36: =G27+G34 -> 2117.9955 | H36: =H27+H34 -> 15622.521 | I36: =I27+I34 -> 15622.521 | J36: =J27+J34 -> 15622.521 | ... N36: =N27+N34 -> 42631.572
A37: Founder cash injection | B37: =SUM(C37:N37) -> 40000 | C37: =IF(C$4=Assumptions!$B$34,Assumptions!$B$33,0) -> 40000 | D37: =IF(D$4=Assumptions!$B$34,Assumptions!$B$33,0) -> 0 | E37: =IF(E$4=Assumptions!$B$34,Assumptions!$B$33,0) -> 0 | F37: =IF(F$4=Assumptions!$B$34,Assumptions!$B$33,0) -> 0 | G37: =IF(G$4=Assumptions!$B$34,Assumptions!$B$33,0) -> 0 | H37: =IF(H$4=Assumptions!$B$34,Assumptions!$B$33,0) -> 0 | I37: =IF(I$4=Assumptions!$B$34,Assumptions!$B$33,0) -> 0 | J37: =IF(J$4=Assumptions!$B$34,Assumptions!$B$33,0) -> 0 | ... N37: =IF(N$4=Assumptions!$B$34,Assumptions!$B$33,0) -> 0
A38: Opening cash | C38: =0 -> 0 | D38: =C39 -> 28770 | E38: =D39 -> 13620 | F38: =E39 -> 10737.996 | G38: =F39 -> 12855.991 | H38: =G39 -> 14973.987 | I38: =H39 -> 30596.507 | J38: =I39 -> 46219.029 | K38: =J39 -> 61841.55 | ... N38: =M39 -> 163490.68
A39: Closing cash | C39: =C38+C36+C37 -> 28770 | D39: =D38+D36+D37 -> 13620 | E39: =E38+E36+E37 -> 10737.996 | F39: =F38+F36+F37 -> 12855.991 | G39: =G38+G36+G37 -> 14973.987 | H39: =H38+H36+H37 -> 30596.507 | I39: =I38+I36+I37 -> 46219.029 | J39: =J38+J36+J37 -> 61841.55 | ... N39: =N38+N36+N37 -> 206122.26
A41: Checks and helpers
A42: Cumulative net cash flow (before injection) | C42: =C36 -> -11230 | D42: =C42+D36 -> -26380 | E42: =D42+E36 -> -29262.004 | F42: =E42+F36 -> -27144.009 | G42: =F42+G36 -> -25026.014 | H42: =G42+H36 -> -9403.4925 | I42: =H42+I36 -> 6219.0285 | J42: =I42+J36 -> 21841.55 | K42: =J42+K36 -> 50968.596 | ... N42: =M42+N36 -> 166122.26
A43: Cumulative sales (VAT turnover) | C43: =C10+C11 -> 0 | D43: =C43+D10+D11 -> 0 | E43: =D43+E10+E11 -> 25448.7 | F43: =E43+F10+F11 -> 50897.4 | G43: =F43+G10+G11 -> 76346.1 | H43: =G43+H10+H11 -> 127243.5 | I43: =H43+I10+I11 -> 178140.9 | J43: =I43+J10+J11 -> 229038.3 | K43: =J43+K10+K11 -> 305384.4 | ... N43: =M43+N10+N11 -> 585320.1
A44: Over VAT threshold? (1 = yes) | C44: =IF(C43>Assumptions!$B$29,1,0) -> 0 | D44: =IF(D43>Assumptions!$B$29,1,0) -> 0 | E44: =IF(E43>Assumptions!$B$29,1,0) -> 0 | F44: =IF(F43>Assumptions!$B$29,1,0) -> 0 | G44: =IF(G43>Assumptions!$B$29,1,0) -> 0 | H44: =IF(H43>Assumptions!$B$29,1,0) -> 0 | I44: =IF(I43>Assumptions!$B$29,1,0) -> 0 | J44: =IF(J43>Assumptions!$B$29,1,0) -> 0 | ... N44: =IF(N43>Assumptions!$B$29,1,0) -> 0
A45: Cumulative cash positive? (1 = yes) | C45: =IF(C42>=0,1,0) -> 0 | D45: =IF(D42>=0,1,0) -> 0 | E45: =IF(E42>=0,1,0) -> 0 | F45: =IF(F42>=0,1,0) -> 0 | G45: =IF(G42>=0,1,0) -> 0 | H45: =IF(H42>=0,1,0) -> 0 | I45: =IF(I42>=0,1,0) -> 1 | J45: =IF(J42>=0,1,0) -> 1 | ... N45: =IF(N42>=0,1,0) -> 1
A46: VAT applies from month # | B46: =MIN(Assumptions!B30,IFERROR(MATCH(1,C44:N44,0)+1,13)) -> 13 | C46: Month after cumulative sales pass the threshold, or the voluntary month if earlier. 13 = not in this plan.
A48: Simplifications: refunds for sales in the last 3 months fall after this plan. VAT is paid in the month it arises (SARS works in two-month periods) and only claims input VAT on cost of sales. No income tax is included.

Sheet Base case
A1: Big Jo's Beds: 12-month cashflow, base case
A2: Scenario # (1 Slow, 2 Base, 3 Target) | B2: 2 | C2: All figures in rand incl. VAT. Inflows positive, outflows in brackets.
A4: Month # | C4: =Assumptions!C62 -> 1 | D4: =Assumptions!D62 -> 2 | E4: =Assumptions!E62 -> 3 | F4: =Assumptions!F62 -> 4 | G4: =Assumptions!G62 -> 5 | H4: =Assumptions!H62 -> 6 | I4: =Assumptions!I62 -> 7 | J4: =Assumptions!J62 -> 8 | ... N4: =Assumptions!N62 -> 12
A5: Month | B5: 12 months | C5: =Assumptions!C63 -> Oct 2026 | D5: =Assumptions!D63 -> Nov 2026 | E5: =Assumptions!E63 -> Dec 2026 | F5: =Assumptions!F63 -> Jan 2027 | G5: =Assumptions!G63 -> Feb 2027 | H5: =Assumptions!H63 -> Mar 2027 | I5: =Assumptions!I63 -> Apr 2027 | J5: =Assumptions!J63 -> May 2027 | ... N5: =Assumptions!N63 -> Sep 2027
A6: Sets sold | B6: =SUM(C6:N6) -> 57 | C6: =INDEX(Assumptions!$C$67:$N$69,$B$2,C$4) -> 0 | D6: =INDEX(Assumptions!$C$67:$N$69,$B$2,D$4) -> 1 | E6: =INDEX(Assumptions!$C$67:$N$69,$B$2,E$4) -> 2 | F6: =INDEX(Assumptions!$C$67:$N$69,$B$2,F$4) -> 2 | G6: =INDEX(Assumptions!$C$67:$N$69,$B$2,G$4) -> 3 | H6: =INDEX(Assumptions!$C$67:$N$69,$B$2,H$4) -> 4 | I6: =INDEX(Assumptions!$C$67:$N$69,$B$2,I$4) -> 5 | J6: =INDEX(Assumptions!$C$67:$N$69,$B$2,J$4) -> 6 | ... N6: =INDEX(Assumptions!$C$67:$N$69,$B$2,N$4) -> 10
A7: Price per set | C7: =IF(C$4>=Assumptions!$B$7,Assumptions!$B$6,Assumptions!$B$5) -> 24999 | D7: =IF(D$4>=Assumptions!$B$7,Assumptions!$B$6,Assumptions!$B$5) -> 24999 | E7: =IF(E$4>=Assumptions!$B$7,Assumptions!$B$6,Assumptions!$B$5) -> 24999 | F7: =IF(F$4>=Assumptions!$B$7,Assumptions!$B$6,Assumptions!$B$5) -> 24999 | G7: =IF(G$4>=Assumptions!$B$7,Assumptions!$B$6,Assumptions!$B$5) -> 24999 | H7: =IF(H$4>=Assumptions!$B$7,Assumptions!$B$6,Assumptions!$B$5) -> 24999 | I7: =IF(I$4>=Assumptions!$B$7,Assumptions!$B$6,Assumptions!$B$5) -> 24999 | J7: =IF(J$4>=Assumptions!$B$7,Assumptions!$B$6,Assumptions!$B$5) -> 24999 | ... N7: =IF(N$4>=Assumptions!$B$7,Assumptions!$B$6,Assumptions!$B$5) -> 24999
A9: Cash in
A10: Bed set sales | B10: =SUM(C10:N10) -> 1424943 | C10: =C6*C7 -> 0 | D10: =D6*D7 -> 24999 | E10: =E6*E7 -> 49998 | F10: =F6*F7 -> 49998 | G10: =G6*G7 -> 74997 | H10: =H6*H7 -> 99996 | I10: =I6*I7 -> 124995 | J10: =J6*J7 -> 149994 | ... N10: =N6*N7 -> 249990
A11: Bedding add-ons | B11: =SUM(C11:N11) -> 25632.9 | C11: =C6*Assumptions!$B$8*Assumptions!$B$9 -> 0 | D11: =D6*Assumptions!$B$8*Assumptions!$B$9 -> 449.7 | E11: =E6*Assumptions!$B$8*Assumptions!$B$9 -> 899.4 | F11: =F6*Assumptions!$B$8*Assumptions!$B$9 -> 899.4 | G11: =G6*Assumptions!$B$8*Assumptions!$B$9 -> 1349.1 | H11: =H6*Assumptions!$B$8*Assumptions!$B$9 -> 1798.8 | I11: =I6*Assumptions!$B$8*Assumptions!$B$9 -> 2248.5 | J11: =J6*Assumptions!$B$8*Assumptions!$B$9 -> 2698.2 | ... N11: =N6*Assumptions!$B$8*Assumptions!$B$9 -> 4497
A12: Refunds on returns | B12: =SUM(C12:N12) -> -22499.1 | C12: =IF(C$4>Assumptions!$B$23,-OFFSET(C10,0,-Assumptions!$B$23)*Assumptions!$B$22,0) -> 0 | D12: =IF(D$4>Assumptions!$B$23,-OFFSET(D10,0,-Assumptions!$B$23)*Assumptions!$B$22,0) -> 0 | E12: =IF(E$4>Assumptions!$B$23,-OFFSET(E10,0,-Assumptions!$B$23)*Assumptions!$B$22,0) -> 0 | F12: =IF(F$4>Assumptions!$B$23,-OFFSET(F10,0,-Assumptions!$B$23)*Assumptions!$B$22,0) -> 0 | G12: =IF(G$4>Assumptions!$B$23,-OFFSET(G10,0,-Assumptions!$B$23)*Assumptions!$B$22,0) -> -749.97 | H12: =IF(H$4>Assumptions!$B$23,-OFFSET(H10,0,-Assumptions!$B$23)*Assumptions!$B$22,0) -> -1499.94 | I12: =IF(I$4>Assumptions!$B$23,-OFFSET(I10,0,-Assumptions!$B$23)*Assumptions!$B$22,0) -> -1499.94 | J12: =IF(J$4>Assumptions!$B$23,-OFFSET(J10,0,-Assumptions!$B$23)*Assumptions!$B$22,0) -> -2249.91 | ... N12: =IF(N$4>Assumptions!$B$23,-OFFSET(N10,0,-Assumptions!$B$23)*Assumptions!$B$22,0) -> -5249.79
A13: Total cash in | B13: =SUM(C13:N13) -> 1428076.8 | C13: =SUM(C10:C12) -> 0 | D13: =SUM(D10:D12) -> 25448.7 | E13: =SUM(E10:E12) -> 50897.4 | F13: =SUM(F10:F12) -> 50897.4 | G13: =SUM(G10:G12) -> 75596.13 | H13: =SUM(H10:H12) -> 100294.86 | I13: =SUM(I10:I12) -> 125743.56 | J13: =SUM(J10:J12) -> 150442.29 | ... N13: =SUM(N10:N12) -> 249237.21
A15: Cost of each sale
A16: PBS mattress and base | B16: =SUM(C16:N16) -> -452010 | C16: =-C6*(Assumptions!$B$13+Assumptions!$B$14)*(1-Assumptions!$B$15) -> 0 | D16: =-D6*(Assumptions!$B$13+Assumptions!$B$14)*(1-Assumptions!$B$15) -> -7930 | E16: =-E6*(Assumptions!$B$13+Assumptions!$B$14)*(1-Assumptions!$B$15) -> -15860 | F16: =-F6*(Assumptions!$B$13+Assumptions!$B$14)*(1-Assumptions!$B$15) -> -15860 | G16: =-G6*(Assumptions!$B$13+Assumptions!$B$14)*(1-Assumptions!$B$15) -> -23790 | H16: =-H6*(Assumptions!$B$13+Assumptions!$B$14)*(1-Assumptions!$B$15) -> -31720 | I16: =-I6*(Assumptions!$B$13+Assumptions!$B$14)*(1-Assumptions!$B$15) -> -39650 | J16: =-J6*(Assumptions!$B$13+Assumptions!$B$14)*(1-Assumptions!$B$15) -> -47580 | ... N16: =-N6*(Assumptions!$B$13+Assumptions!$B$14)*(1-Assumptions!$B$15) -> -79300
A17: Delivery and setup | B17: =SUM(C17:N17) -> -25650 | C17: =-C6*Assumptions!$B$16 -> 0 | D17: =-D6*Assumptions!$B$16 -> -450 | E17: =-E6*Assumptions!$B$16 -> -900 | F17: =-F6*Assumptions!$B$16 -> -900 | G17: =-G6*Assumptions!$B$16 -> -1350 | H17: =-H6*Assumptions!$B$16 -> -1800 | I17: =-I6*Assumptions!$B$16 -> -2250 | J17: =-J6*Assumptions!$B$16 -> -2700 | ... N17: =-N6*Assumptions!$B$16 -> -4500
A18: Old-bed removal | B18: =SUM(C18:N18) -> -17100 | C18: =-C6*Assumptions!$B$17 -> 0 | D18: =-D6*Assumptions!$B$17 -> -300 | E18: =-E6*Assumptions!$B$17 -> -600 | F18: =-F6*Assumptions!$B$17 -> -600 | G18: =-G6*Assumptions!$B$17 -> -900 | H18: =-H6*Assumptions!$B$17 -> -1200 | I18: =-I6*Assumptions!$B$17 -> -1500 | J18: =-J6*Assumptions!$B$17 -> -1800 | ... N18: =-N6*Assumptions!$B$17 -> -3000
A19: Bedding in the box | B19: =SUM(C19:N19) -> -57000 | C19: =-C6*Assumptions!$B$18 -> 0 | D19: =-D6*Assumptions!$B$18 -> -1000 | E19: =-E6*Assumptions!$B$18 -> -2000 | F19: =-F6*Assumptions!$B$18 -> -2000 | G19: =-G6*Assumptions!$B$18 -> -3000 | H19: =-H6*Assumptions!$B$18 -> -4000 | I19: =-I6*Assumptions!$B$18 -> -5000 | J19: =-J6*Assumptions!$B$18 -> -6000 | ... N19: =-N6*Assumptions!$B$18 -> -10000
A20: Packaging and cards | B20: =SUM(C20:N20) -> -8550 | C20: =-C6*Assumptions!$B$19 -> 0 | D20: =-D6*Assumptions!$B$19 -> -150 | E20: =-E6*Assumptions!$B$19 -> -300 | F20: =-F6*Assumptions!$B$19 -> -300 | G20: =-G6*Assumptions!$B$19 -> -450 | H20: =-H6*Assumptions!$B$19 -> -600 | I20: =-I6*Assumptions!$B$19 -> -750 | J20: =-J6*Assumptions!$B$19 -> -900 | ... N20: =-N6*Assumptions!$B$19 -> -1500
A21: Bedding add-on cost | B21: =SUM(C21:N21) -> -11970 | C21: =-C6*Assumptions!$B$8*Assumptions!$B$10 -> 0 | D21: =-D6*Assumptions!$B$8*Assumptions!$B$10 -> -210 | E21: =-E6*Assumptions!$B$8*Assumptions!$B$10 -> -420 | F21: =-F6*Assumptions!$B$8*Assumptions!$B$10 -> -420 | G21: =-G6*Assumptions!$B$8*Assumptions!$B$10 -> -630 | H21: =-H6*Assumptions!$B$8*Assumptions!$B$10 -> -840 | I21: =-I6*Assumptions!$B$8*Assumptions!$B$10 -> -1050 | J21: =-J6*Assumptions!$B$8*Assumptions!$B$10 -> -1260 | ... N21: =-N6*Assumptions!$B$8*Assumptions!$B$10 -> -2100
A22: Collecting returned sets | B22: =SUM(C22:N22) -> -405 | C22: =IF(C$4>Assumptions!$B$23,-OFFSET(C6,0,-Assumptions!$B$23)*Assumptions!$B$22*Assumptions!$B$24,0) -> 0 | D22: =IF(D$4>Assumptions!$B$23,-OFFSET(D6,0,-Assumptions!$B$23)*Assumptions!$B$22*Assumptions!$B$24,0) -> 0 | E22: =IF(E$4>Assumptions!$B$23,-OFFSET(E6,0,-Assumptions!$B$23)*Assumptions!$B$22*Assumptions!$B$24,0) -> 0 | F22: =IF(F$4>Assumptions!$B$23,-OFFSET(F6,0,-Assumptions!$B$23)*Assumptions!$B$22*Assumptions!$B$24,0) -> 0 | G22: =IF(G$4>Assumptions!$B$23,-OFFSET(G6,0,-Assumptions!$B$23)*Assumptions!$B$22*Assumptions!$B$24,0) -> -13.5 | H22: =IF(H$4>Assumptions!$B$23,-OFFSET(H6,0,-Assumptions!$B$23)*Assumptions!$B$22*Assumptions!$B$24,0) -> -27 | I22: =IF(I$4>Assumptions!$B$23,-OFFSET(I6,0,-Assumptions!$B$23)*Assumptions!$B$22*Assumptions!$B$24,0) -> -27 | J22: =IF(J$4>Assumptions!$B$23,-OFFSET(J6,0,-Assumptions!$B$23)*Assumptions!$B$22*Assumptions!$B$24,0) -> -40.5 | ... N22: =IF(N$4>Assumptions!$B$23,-OFFSET(N6,0,-Assumptions!$B$23)*Assumptions!$B$22*Assumptions!$B$24,0) -> -94.5
A23: Payment fees | B23: =SUM(C23:N23) -> -50770.156 | C23: =-(C10+C11)*Assumptions!$B$20 -> 0 | D23: =-(D10+D11)*Assumptions!$B$20 -> -890.7045 | E23: =-(E10+E11)*Assumptions!$B$20 -> -1781.409 | F23: =-(F10+F11)*Assumptions!$B$20 -> -1781.409 | G23: =-(G10+G11)*Assumptions!$B$20 -> -2672.1135 | H23: =-(H10+H11)*Assumptions!$B$20 -> -3562.818 | I23: =-(I10+I11)*Assumptions!$B$20 -> -4453.5225 | J23: =-(J10+J11)*Assumptions!$B$20 -> -5344.227 | ... N23: =-(N10+N11)*Assumptions!$B$20 -> -8907.045
A24: Warranty reserve (set aside) | B24: =SUM(C24:N24) -> -14250 | C24: =-C6*Assumptions!$B$21 -> 0 | D24: =-D6*Assumptions!$B$21 -> -250 | E24: =-E6*Assumptions!$B$21 -> -500 | F24: =-F6*Assumptions!$B$21 -> -500 | G24: =-G6*Assumptions!$B$21 -> -750 | H24: =-H6*Assumptions!$B$21 -> -1000 | I24: =-I6*Assumptions!$B$21 -> -1250 | J24: =-J6*Assumptions!$B$21 -> -1500 | ... N24: =-N6*Assumptions!$B$21 -> -2500
A25: Total cost of sales | B25: =SUM(C25:N25) -> -637705.16 | C25: =SUM(C16:C24) -> 0 | D25: =SUM(D16:D24) -> -11180.704 | E25: =SUM(E16:E24) -> -22361.409 | F25: =SUM(F16:F24) -> -22361.409 | G25: =SUM(G16:G24) -> -33555.613 | H25: =SUM(H16:H24) -> -44749.818 | I25: =SUM(I16:I24) -> -55930.522 | J25: =SUM(J16:J24) -> -67124.727 | ... N25: =SUM(N16:N24) -> -111901.54
A27: Gross contribution | B27: =SUM(C27:N27) -> 790371.64 | C27: =C13+C25 -> 0 | D27: =D13+D25 -> 14267.996 | E27: =E13+E25 -> 28535.991 | F27: =F13+F25 -> 28535.991 | G27: =G13+G25 -> 42040.516 | H27: =H13+H25 -> 55545.042 | I27: =I13+I25 -> 69813.038 | J27: =J13+J25 -> 83317.563 | ... N27: =N13+N25 -> 137335.67
A29: Overheads and launch
A30: Marketing | B30: =SUM(C30:N30) -> -108000 | C30: =-Assumptions!C64 -> 0 | D30: =-Assumptions!D64 -> -8000 | E30: =-Assumptions!E64 -> -10000 | F30: =-Assumptions!F64 -> -10000 | G30: =-Assumptions!G64 -> -10000 | H30: =-Assumptions!H64 -> -10000 | I30: =-Assumptions!I64 -> -10000 | J30: =-Assumptions!J64 -> -10000 | ... N30: =-Assumptions!N64 -> -10000
A31: Fixed running costs | B31: =SUM(C31:N31) -> -24500 | C31: =-SUMPRODUCT((Assumptions!$C$38:$C$43<=C$4)*Assumptions!$B$38:$B$43) -> -850 | D31: =-SUMPRODUCT((Assumptions!$C$38:$C$43<=D$4)*Assumptions!$B$38:$B$43) -> -2150 | E31: =-SUMPRODUCT((Assumptions!$C$38:$C$43<=E$4)*Assumptions!$B$38:$B$43) -> -2150 | F31: =-SUMPRODUCT((Assumptions!$C$38:$C$43<=F$4)*Assumptions!$B$38:$B$43) -> -2150 | G31: =-SUMPRODUCT((Assumptions!$C$38:$C$43<=G$4)*Assumptions!$B$38:$B$43) -> -2150 | H31: =-SUMPRODUCT((Assumptions!$C$38:$C$43<=H$4)*Assumptions!$B$38:$B$43) -> -2150 | I31: =-SUMPRODUCT((Assumptions!$C$38:$C$43<=I$4)*Assumptions!$B$38:$B$43) -> -2150 | J31: =-SUMPRODUCT((Assumptions!$C$38:$C$43<=J$4)*Assumptions!$B$38:$B$43) -> -2150 | ... N31: =-SUMPRODUCT((Assumptions!$C$38:$C$43<=N$4)*Assumptions!$B$38:$B$43) -> -2150
A32: One-off launch costs | B32: =SUM(C32:N32) -> -20380 | C32: =-SUMIF(Assumptions!$C$48:$C$58,C$4,Assumptions!$B$48:$B$58) -> -10380 | D32: =-SUMIF(Assumptions!$C$48:$C$58,D$4,Assumptions!$B$48:$B$58) -> -5000 | E32: =-SUMIF(Assumptions!$C$48:$C$58,E$4,Assumptions!$B$48:$B$58) -> -5000 | F32: =-SUMIF(Assumptions!$C$48:$C$58,F$4,Assumptions!$B$48:$B$58) -> 0 | G32: =-SUMIF(Assumptions!$C$48:$C$58,G$4,Assumptions!$B$48:$B$58) -> 0 | H32: =-SUMIF(Assumptions!$C$48:$C$58,H$4,Assumptions!$B$48:$B$58) -> 0 | I32: =-SUMIF(Assumptions!$C$48:$C$58,I$4,Assumptions!$B$48:$B$58) -> 0 | J32: =-SUMIF(Assumptions!$C$48:$C$58,J$4,Assumptions!$B$48:$B$58) -> 0 | ... N32: =-SUMIF(Assumptions!$C$48:$C$58,N$4,Assumptions!$B$48:$B$58) -> 0
A33: VAT paid to SARS (net) | B33: =SUM(C33:N33) -> 0 | C33: =IF(C$4>=$B$46,-(C13+SUM(C16:C22))*Assumptions!$B$28/(1+Assumptions!$B$28),0) -> 0 | D33: =IF(D$4>=$B$46,-(D13+SUM(D16:D22))*Assumptions!$B$28/(1+Assumptions!$B$28),0) -> 0 | E33: =IF(E$4>=$B$46,-(E13+SUM(E16:E22))*Assumptions!$B$28/(1+Assumptions!$B$28),0) -> 0 | F33: =IF(F$4>=$B$46,-(F13+SUM(F16:F22))*Assumptions!$B$28/(1+Assumptions!$B$28),0) -> 0 | G33: =IF(G$4>=$B$46,-(G13+SUM(G16:G22))*Assumptions!$B$28/(1+Assumptions!$B$28),0) -> 0 | H33: =IF(H$4>=$B$46,-(H13+SUM(H16:H22))*Assumptions!$B$28/(1+Assumptions!$B$28),0) -> 0 | I33: =IF(I$4>=$B$46,-(I13+SUM(I16:I22))*Assumptions!$B$28/(1+Assumptions!$B$28),0) -> 0 | J33: =IF(J$4>=$B$46,-(J13+SUM(J16:J22))*Assumptions!$B$28/(1+Assumptions!$B$28),0) -> 0 | ... N33: =IF(N$4>=$B$46,-(N13+SUM(N16:N22))*Assumptions!$B$28/(1+Assumptions!$B$28),0) -> 0
A34: Total overheads and launch | B34: =SUM(C34:N34) -> -152880 | C34: =SUM(C30:C33) -> -11230 | D34: =SUM(D30:D33) -> -15150 | E34: =SUM(E30:E33) -> -17150 | F34: =SUM(F30:F33) -> -12150 | G34: =SUM(G30:G33) -> -12150 | H34: =SUM(H30:H33) -> -12150 | I34: =SUM(I30:I33) -> -12150 | J34: =SUM(J30:J33) -> -12150 | ... N34: =SUM(N30:N33) -> -12150
A36: Net cash flow | B36: =SUM(C36:N36) -> 637491.64 | C36: =C27+C34 -> -11230 | D36: =D27+D34 -> -882.0045 | E36: =E27+E34 -> 11385.991 | F36: =F27+F34 -> 16385.991 | G36: =G27+G34 -> 29890.517 | H36: =H27+H34 -> 43395.042 | I36: =I27+I34 -> 57663.037 | J36: =J27+J34 -> 71167.563 | ... N36: =N27+N34 -> 125185.66
A37: Founder cash injection | B37: =SUM(C37:N37) -> 40000 | C37: =IF(C$4=Assumptions!$B$34,Assumptions!$B$33,0) -> 40000 | D37: =IF(D$4=Assumptions!$B$34,Assumptions!$B$33,0) -> 0 | E37: =IF(E$4=Assumptions!$B$34,Assumptions!$B$33,0) -> 0 | F37: =IF(F$4=Assumptions!$B$34,Assumptions!$B$33,0) -> 0 | G37: =IF(G$4=Assumptions!$B$34,Assumptions!$B$33,0) -> 0 | H37: =IF(H$4=Assumptions!$B$34,Assumptions!$B$33,0) -> 0 | I37: =IF(I$4=Assumptions!$B$34,Assumptions!$B$33,0) -> 0 | J37: =IF(J$4=Assumptions!$B$34,Assumptions!$B$33,0) -> 0 | ... N37: =IF(N$4=Assumptions!$B$34,Assumptions!$B$33,0) -> 0
A38: Opening cash | C38: =0 -> 0 | D38: =C39 -> 28770 | E38: =D39 -> 27887.996 | F38: =E39 -> 39273.986 | G38: =F39 -> 55659.978 | H38: =G39 -> 85550.494 | I38: =H39 -> 128945.54 | J38: =I39 -> 186608.57 | K38: =J39 -> 257776.14 | ... N38: =M39 -> 552305.98
A39: Closing cash | C39: =C38+C36+C37 -> 28770 | D39: =D38+D36+D37 -> 27887.996 | E39: =E38+E36+E37 -> 39273.986 | F39: =F38+F36+F37 -> 55659.978 | G39: =G38+G36+G37 -> 85550.494 | H39: =H38+H36+H37 -> 128945.54 | I39: =I38+I36+I37 -> 186608.57 | J39: =J38+J36+J37 -> 257776.14 | ... N39: =N38+N36+N37 -> 677491.64
A41: Checks and helpers
A42: Cumulative net cash flow (before injection) | C42: =C36 -> -11230 | D42: =C42+D36 -> -12112.004 | E42: =D42+E36 -> -726.0135 | F42: =E42+F36 -> 15659.978 | G42: =F42+G36 -> 45550.494 | H42: =G42+H36 -> 88945.536 | I42: =H42+I36 -> 146608.57 | J42: =I42+J36 -> 217776.14 | K42: =J42+K36 -> 302448.22 | ... N42: =M42+N36 -> 637491.64
A43: Cumulative sales (VAT turnover) | C43: =C10+C11 -> 0 | D43: =C43+D10+D11 -> 25448.7 | E43: =D43+E10+E11 -> 76346.1 | F43: =E43+F10+F11 -> 127243.5 | G43: =F43+G10+G11 -> 203589.6 | H43: =G43+H10+H11 -> 305384.4 | I43: =H43+I10+I11 -> 432627.9 | J43: =I43+J10+J11 -> 585320.1 | K43: =J43+K10+K11 -> 763461 | ... N43: =M43+N10+N11 -> 1450575.9
A44: Over VAT threshold? (1 = yes) | C44: =IF(C43>Assumptions!$B$29,1,0) -> 0 | D44: =IF(D43>Assumptions!$B$29,1,0) -> 0 | E44: =IF(E43>Assumptions!$B$29,1,0) -> 0 | F44: =IF(F43>Assumptions!$B$29,1,0) -> 0 | G44: =IF(G43>Assumptions!$B$29,1,0) -> 0 | H44: =IF(H43>Assumptions!$B$29,1,0) -> 0 | I44: =IF(I43>Assumptions!$B$29,1,0) -> 0 | J44: =IF(J43>Assumptions!$B$29,1,0) -> 0 | ... N44: =IF(N43>Assumptions!$B$29,1,0) -> 0
A45: Cumulative cash positive? (1 = yes) | C45: =IF(C42>=0,1,0) -> 0 | D45: =IF(D42>=0,1,0) -> 0 | E45: =IF(E42>=0,1,0) -> 0 | F45: =IF(F42>=0,1,0) -> 1 | G45: =IF(G42>=0,1,0) -> 1 | H45: =IF(H42>=0,1,0) -> 1 | I45: =IF(I42>=0,1,0) -> 1 | J45: =IF(J42>=0,1,0) -> 1 | ... N45: =IF(N42>=0,1,0) -> 1
A46: VAT applies from month # | B46: =MIN(Assumptions!B30,IFERROR(MATCH(1,C44:N44,0)+1,13)) -> 13 | C46: Month after cumulative sales pass the threshold, or the voluntary month if earlier. 13 = not in this plan.
A48: Simplifications: refunds for sales in the last 3 months fall after this plan. VAT is paid in the month it arises (SARS works in two-month periods) and only claims input VAT on cost of sales. No income tax is included.

Sheet Target case
A1: Big Jo's Beds: 12-month cashflow, target case
A2: Scenario # (1 Slow, 2 Base, 3 Target) | B2: 3 | C2: All figures in rand incl. VAT. Inflows positive, outflows in brackets.
A4: Month # | C4: =Assumptions!C62 -> 1 | D4: =Assumptions!D62 -> 2 | E4: =Assumptions!E62 -> 3 | F4: =Assumptions!F62 -> 4 | G4: =Assumptions!G62 -> 5 | H4: =Assumptions!H62 -> 6 | I4: =Assumptions!I62 -> 7 | J4: =Assumptions!J62 -> 8 | ... N4: =Assumptions!N62 -> 12
A5: Month | B5: 12 months | C5: =Assumptions!C63 -> Oct 2026 | D5: =Assumptions!D63 -> Nov 2026 | E5: =Assumptions!E63 -> Dec 2026 | F5: =Assumptions!F63 -> Jan 2027 | G5: =Assumptions!G63 -> Feb 2027 | H5: =Assumptions!H63 -> Mar 2027 | I5: =Assumptions!I63 -> Apr 2027 | J5: =Assumptions!J63 -> May 2027 | ... N5: =Assumptions!N63 -> Sep 2027
A6: Sets sold | B6: =SUM(C6:N6) -> 122 | C6: =INDEX(Assumptions!$C$67:$N$69,$B$2,C$4) -> 0 | D6: =INDEX(Assumptions!$C$67:$N$69,$B$2,D$4) -> 2 | E6: =INDEX(Assumptions!$C$67:$N$69,$B$2,E$4) -> 4 | F6: =INDEX(Assumptions!$C$67:$N$69,$B$2,F$4) -> 5 | G6: =INDEX(Assumptions!$C$67:$N$69,$B$2,G$4) -> 7 | H6: =INDEX(Assumptions!$C$67:$N$69,$B$2,H$4) -> 9 | I6: =INDEX(Assumptions!$C$67:$N$69,$B$2,I$4) -> 11 | J6: =INDEX(Assumptions!$C$67:$N$69,$B$2,J$4) -> 13 | ... N6: =INDEX(Assumptions!$C$67:$N$69,$B$2,N$4) -> 20
A7: Price per set | C7: =IF(C$4>=Assumptions!$B$7,Assumptions!$B$6,Assumptions!$B$5) -> 24999 | D7: =IF(D$4>=Assumptions!$B$7,Assumptions!$B$6,Assumptions!$B$5) -> 24999 | E7: =IF(E$4>=Assumptions!$B$7,Assumptions!$B$6,Assumptions!$B$5) -> 24999 | F7: =IF(F$4>=Assumptions!$B$7,Assumptions!$B$6,Assumptions!$B$5) -> 24999 | G7: =IF(G$4>=Assumptions!$B$7,Assumptions!$B$6,Assumptions!$B$5) -> 24999 | H7: =IF(H$4>=Assumptions!$B$7,Assumptions!$B$6,Assumptions!$B$5) -> 24999 | I7: =IF(I$4>=Assumptions!$B$7,Assumptions!$B$6,Assumptions!$B$5) -> 24999 | J7: =IF(J$4>=Assumptions!$B$7,Assumptions!$B$6,Assumptions!$B$5) -> 24999 | ... N7: =IF(N$4>=Assumptions!$B$7,Assumptions!$B$6,Assumptions!$B$5) -> 24999
A9: Cash in
A10: Bed set sales | B10: =SUM(C10:N10) -> 3049878 | C10: =C6*C7 -> 0 | D10: =D6*D7 -> 49998 | E10: =E6*E7 -> 99996 | F10: =F6*F7 -> 124995 | G10: =G6*G7 -> 174993 | H10: =H6*H7 -> 224991 | I10: =I6*I7 -> 274989 | J10: =J6*J7 -> 324987 | ... N10: =N6*N7 -> 499980
A11: Bedding add-ons | B11: =SUM(C11:N11) -> 54863.4 | C11: =C6*Assumptions!$B$8*Assumptions!$B$9 -> 0 | D11: =D6*Assumptions!$B$8*Assumptions!$B$9 -> 899.4 | E11: =E6*Assumptions!$B$8*Assumptions!$B$9 -> 1798.8 | F11: =F6*Assumptions!$B$8*Assumptions!$B$9 -> 2248.5 | G11: =G6*Assumptions!$B$8*Assumptions!$B$9 -> 3147.9 | H11: =H6*Assumptions!$B$8*Assumptions!$B$9 -> 4047.3 | I11: =I6*Assumptions!$B$8*Assumptions!$B$9 -> 4946.7 | J11: =J6*Assumptions!$B$8*Assumptions!$B$9 -> 5846.1 | ... N11: =N6*Assumptions!$B$8*Assumptions!$B$9 -> 8994
A12: Refunds on returns | B12: =SUM(C12:N12) -> -49498.02 | C12: =IF(C$4>Assumptions!$B$23,-OFFSET(C10,0,-Assumptions!$B$23)*Assumptions!$B$22,0) -> 0 | D12: =IF(D$4>Assumptions!$B$23,-OFFSET(D10,0,-Assumptions!$B$23)*Assumptions!$B$22,0) -> 0 | E12: =IF(E$4>Assumptions!$B$23,-OFFSET(E10,0,-Assumptions!$B$23)*Assumptions!$B$22,0) -> 0 | F12: =IF(F$4>Assumptions!$B$23,-OFFSET(F10,0,-Assumptions!$B$23)*Assumptions!$B$22,0) -> 0 | G12: =IF(G$4>Assumptions!$B$23,-OFFSET(G10,0,-Assumptions!$B$23)*Assumptions!$B$22,0) -> -1499.94 | H12: =IF(H$4>Assumptions!$B$23,-OFFSET(H10,0,-Assumptions!$B$23)*Assumptions!$B$22,0) -> -2999.88 | I12: =IF(I$4>Assumptions!$B$23,-OFFSET(I10,0,-Assumptions!$B$23)*Assumptions!$B$22,0) -> -3749.85 | J12: =IF(J$4>Assumptions!$B$23,-OFFSET(J10,0,-Assumptions!$B$23)*Assumptions!$B$22,0) -> -5249.79 | ... N12: =IF(N$4>Assumptions!$B$23,-OFFSET(N10,0,-Assumptions!$B$23)*Assumptions!$B$22,0) -> -11249.55
A13: Total cash in | B13: =SUM(C13:N13) -> 3055243.4 | C13: =SUM(C10:C12) -> 0 | D13: =SUM(D10:D12) -> 50897.4 | E13: =SUM(E10:E12) -> 101794.8 | F13: =SUM(F10:F12) -> 127243.5 | G13: =SUM(G10:G12) -> 176640.96 | H13: =SUM(H10:H12) -> 226038.42 | I13: =SUM(I10:I12) -> 276185.85 | J13: =SUM(J10:J12) -> 325583.31 | ... N13: =SUM(N10:N12) -> 497724.45
A15: Cost of each sale
A16: PBS mattress and base | B16: =SUM(C16:N16) -> -967460 | C16: =-C6*(Assumptions!$B$13+Assumptions!$B$14)*(1-Assumptions!$B$15) -> 0 | D16: =-D6*(Assumptions!$B$13+Assumptions!$B$14)*(1-Assumptions!$B$15) -> -15860 | E16: =-E6*(Assumptions!$B$13+Assumptions!$B$14)*(1-Assumptions!$B$15) -> -31720 | F16: =-F6*(Assumptions!$B$13+Assumptions!$B$14)*(1-Assumptions!$B$15) -> -39650 | G16: =-G6*(Assumptions!$B$13+Assumptions!$B$14)*(1-Assumptions!$B$15) -> -55510 | H16: =-H6*(Assumptions!$B$13+Assumptions!$B$14)*(1-Assumptions!$B$15) -> -71370 | I16: =-I6*(Assumptions!$B$13+Assumptions!$B$14)*(1-Assumptions!$B$15) -> -87230 | J16: =-J6*(Assumptions!$B$13+Assumptions!$B$14)*(1-Assumptions!$B$15) -> -103090 | ... N16: =-N6*(Assumptions!$B$13+Assumptions!$B$14)*(1-Assumptions!$B$15) -> -158600
A17: Delivery and setup | B17: =SUM(C17:N17) -> -54900 | C17: =-C6*Assumptions!$B$16 -> 0 | D17: =-D6*Assumptions!$B$16 -> -900 | E17: =-E6*Assumptions!$B$16 -> -1800 | F17: =-F6*Assumptions!$B$16 -> -2250 | G17: =-G6*Assumptions!$B$16 -> -3150 | H17: =-H6*Assumptions!$B$16 -> -4050 | I17: =-I6*Assumptions!$B$16 -> -4950 | J17: =-J6*Assumptions!$B$16 -> -5850 | ... N17: =-N6*Assumptions!$B$16 -> -9000
A18: Old-bed removal | B18: =SUM(C18:N18) -> -36600 | C18: =-C6*Assumptions!$B$17 -> 0 | D18: =-D6*Assumptions!$B$17 -> -600 | E18: =-E6*Assumptions!$B$17 -> -1200 | F18: =-F6*Assumptions!$B$17 -> -1500 | G18: =-G6*Assumptions!$B$17 -> -2100 | H18: =-H6*Assumptions!$B$17 -> -2700 | I18: =-I6*Assumptions!$B$17 -> -3300 | J18: =-J6*Assumptions!$B$17 -> -3900 | ... N18: =-N6*Assumptions!$B$17 -> -6000
A19: Bedding in the box | B19: =SUM(C19:N19) -> -122000 | C19: =-C6*Assumptions!$B$18 -> 0 | D19: =-D6*Assumptions!$B$18 -> -2000 | E19: =-E6*Assumptions!$B$18 -> -4000 | F19: =-F6*Assumptions!$B$18 -> -5000 | G19: =-G6*Assumptions!$B$18 -> -7000 | H19: =-H6*Assumptions!$B$18 -> -9000 | I19: =-I6*Assumptions!$B$18 -> -11000 | J19: =-J6*Assumptions!$B$18 -> -13000 | ... N19: =-N6*Assumptions!$B$18 -> -20000
A20: Packaging and cards | B20: =SUM(C20:N20) -> -18300 | C20: =-C6*Assumptions!$B$19 -> 0 | D20: =-D6*Assumptions!$B$19 -> -300 | E20: =-E6*Assumptions!$B$19 -> -600 | F20: =-F6*Assumptions!$B$19 -> -750 | G20: =-G6*Assumptions!$B$19 -> -1050 | H20: =-H6*Assumptions!$B$19 -> -1350 | I20: =-I6*Assumptions!$B$19 -> -1650 | J20: =-J6*Assumptions!$B$19 -> -1950 | ... N20: =-N6*Assumptions!$B$19 -> -3000
A21: Bedding add-on cost | B21: =SUM(C21:N21) -> -25620 | C21: =-C6*Assumptions!$B$8*Assumptions!$B$10 -> 0 | D21: =-D6*Assumptions!$B$8*Assumptions!$B$10 -> -420 | E21: =-E6*Assumptions!$B$8*Assumptions!$B$10 -> -840 | F21: =-F6*Assumptions!$B$8*Assumptions!$B$10 -> -1050 | G21: =-G6*Assumptions!$B$8*Assumptions!$B$10 -> -1470 | H21: =-H6*Assumptions!$B$8*Assumptions!$B$10 -> -1890 | I21: =-I6*Assumptions!$B$8*Assumptions!$B$10 -> -2310 | J21: =-J6*Assumptions!$B$8*Assumptions!$B$10 -> -2730 | ... N21: =-N6*Assumptions!$B$8*Assumptions!$B$10 -> -4200
A22: Collecting returned sets | B22: =SUM(C22:N22) -> -891 | C22: =IF(C$4>Assumptions!$B$23,-OFFSET(C6,0,-Assumptions!$B$23)*Assumptions!$B$22*Assumptions!$B$24,0) -> 0 | D22: =IF(D$4>Assumptions!$B$23,-OFFSET(D6,0,-Assumptions!$B$23)*Assumptions!$B$22*Assumptions!$B$24,0) -> 0 | E22: =IF(E$4>Assumptions!$B$23,-OFFSET(E6,0,-Assumptions!$B$23)*Assumptions!$B$22*Assumptions!$B$24,0) -> 0 | F22: =IF(F$4>Assumptions!$B$23,-OFFSET(F6,0,-Assumptions!$B$23)*Assumptions!$B$22*Assumptions!$B$24,0) -> 0 | G22: =IF(G$4>Assumptions!$B$23,-OFFSET(G6,0,-Assumptions!$B$23)*Assumptions!$B$22*Assumptions!$B$24,0) -> -27 | H22: =IF(H$4>Assumptions!$B$23,-OFFSET(H6,0,-Assumptions!$B$23)*Assumptions!$B$22*Assumptions!$B$24,0) -> -54 | I22: =IF(I$4>Assumptions!$B$23,-OFFSET(I6,0,-Assumptions!$B$23)*Assumptions!$B$22*Assumptions!$B$24,0) -> -67.5 | J22: =IF(J$4>Assumptions!$B$23,-OFFSET(J6,0,-Assumptions!$B$23)*Assumptions!$B$22*Assumptions!$B$24,0) -> -94.5 | ... N22: =IF(N$4>Assumptions!$B$23,-OFFSET(N6,0,-Assumptions!$B$23)*Assumptions!$B$22*Assumptions!$B$24,0) -> -202.5
A23: Payment fees | B23: =SUM(C23:N23) -> -108665.95 | C23: =-(C10+C11)*Assumptions!$B$20 -> 0 | D23: =-(D10+D11)*Assumptions!$B$20 -> -1781.409 | E23: =-(E10+E11)*Assumptions!$B$20 -> -3562.818 | F23: =-(F10+F11)*Assumptions!$B$20 -> -4453.5225 | G23: =-(G10+G11)*Assumptions!$B$20 -> -6234.9315 | H23: =-(H10+H11)*Assumptions!$B$20 -> -8016.3405 | I23: =-(I10+I11)*Assumptions!$B$20 -> -9797.7495 | J23: =-(J10+J11)*Assumptions!$B$20 -> -11579.158 | ... N23: =-(N10+N11)*Assumptions!$B$20 -> -17814.09
A24: Warranty reserve (set aside) | B24: =SUM(C24:N24) -> -30500 | C24: =-C6*Assumptions!$B$21 -> 0 | D24: =-D6*Assumptions!$B$21 -> -500 | E24: =-E6*Assumptions!$B$21 -> -1000 | F24: =-F6*Assumptions!$B$21 -> -1250 | G24: =-G6*Assumptions!$B$21 -> -1750 | H24: =-H6*Assumptions!$B$21 -> -2250 | I24: =-I6*Assumptions!$B$21 -> -2750 | J24: =-J6*Assumptions!$B$21 -> -3250 | ... N24: =-N6*Assumptions!$B$21 -> -5000
A25: Total cost of sales | B25: =SUM(C25:N25) -> -1364936.9 | C25: =SUM(C16:C24) -> 0 | D25: =SUM(D16:D24) -> -22361.409 | E25: =SUM(E16:E24) -> -44722.818 | F25: =SUM(F16:F24) -> -55903.522 | G25: =SUM(G16:G24) -> -78291.932 | H25: =SUM(H16:H24) -> -100680.34 | I25: =SUM(I16:I24) -> -123055.25 | J25: =SUM(J16:J24) -> -145443.66 | ... N25: =SUM(N16:N24) -> -223816.59
A27: Gross contribution | B27: =SUM(C27:N27) -> 1690306.4 | C27: =C13+C25 -> 0 | D27: =D13+D25 -> 28535.991 | E27: =E13+E25 -> 57071.982 | F27: =F13+F25 -> 71339.977 | G27: =G13+G25 -> 98349.029 | H27: =H13+H25 -> 125358.08 | I27: =I13+I25 -> 153130.6 | J27: =J13+J25 -> 180139.65 | ... N27: =N13+N25 -> 273907.86
A29: Overheads and launch
A30: Marketing | B30: =SUM(C30:N30) -> -108000 | C30: =-Assumptions!C64 -> 0 | D30: =-Assumptions!D64 -> -8000 | E30: =-Assumptions!E64 -> -10000 | F30: =-Assumptions!F64 -> -10000 | G30: =-Assumptions!G64 -> -10000 | H30: =-Assumptions!H64 -> -10000 | I30: =-Assumptions!I64 -> -10000 | J30: =-Assumptions!J64 -> -10000 | ... N30: =-Assumptions!N64 -> -10000
A31: Fixed running costs | B31: =SUM(C31:N31) -> -24500 | C31: =-SUMPRODUCT((Assumptions!$C$38:$C$43<=C$4)*Assumptions!$B$38:$B$43) -> -850 | D31: =-SUMPRODUCT((Assumptions!$C$38:$C$43<=D$4)*Assumptions!$B$38:$B$43) -> -2150 | E31: =-SUMPRODUCT((Assumptions!$C$38:$C$43<=E$4)*Assumptions!$B$38:$B$43) -> -2150 | F31: =-SUMPRODUCT((Assumptions!$C$38:$C$43<=F$4)*Assumptions!$B$38:$B$43) -> -2150 | G31: =-SUMPRODUCT((Assumptions!$C$38:$C$43<=G$4)*Assumptions!$B$38:$B$43) -> -2150 | H31: =-SUMPRODUCT((Assumptions!$C$38:$C$43<=H$4)*Assumptions!$B$38:$B$43) -> -2150 | I31: =-SUMPRODUCT((Assumptions!$C$38:$C$43<=I$4)*Assumptions!$B$38:$B$43) -> -2150 | J31: =-SUMPRODUCT((Assumptions!$C$38:$C$43<=J$4)*Assumptions!$B$38:$B$43) -> -2150 | ... N31: =-SUMPRODUCT((Assumptions!$C$38:$C$43<=N$4)*Assumptions!$B$38:$B$43) -> -2150
A32: One-off launch costs | B32: =SUM(C32:N32) -> -20380 | C32: =-SUMIF(Assumptions!$C$48:$C$58,C$4,Assumptions!$B$48:$B$58) -> -10380 | D32: =-SUMIF(Assumptions!$C$48:$C$58,D$4,Assumptions!$B$48:$B$58) -> -5000 | E32: =-SUMIF(Assumptions!$C$48:$C$58,E$4,Assumptions!$B$48:$B$58) -> -5000 | F32: =-SUMIF(Assumptions!$C$48:$C$58,F$4,Assumptions!$B$48:$B$58) -> 0 | G32: =-SUMIF(Assumptions!$C$48:$C$58,G$4,Assumptions!$B$48:$B$58) -> 0 | H32: =-SUMIF(Assumptions!$C$48:$C$58,H$4,Assumptions!$B$48:$B$58) -> 0 | I32: =-SUMIF(Assumptions!$C$48:$C$58,I$4,Assumptions!$B$48:$B$58) -> 0 | J32: =-SUMIF(Assumptions!$C$48:$C$58,J$4,Assumptions!$B$48:$B$58) -> 0 | ... N32: =-SUMIF(Assumptions!$C$48:$C$58,N$4,Assumptions!$B$48:$B$58) -> 0
A33: VAT paid to SARS (net) | B33: =SUM(C33:N33) -> -38702.863 | C33: =IF(C$4>=$B$46,-(C13+SUM(C16:C22))*Assumptions!$B$28/(1+Assumptions!$B$28),0) -> 0 | D33: =IF(D$4>=$B$46,-(D13+SUM(D16:D22))*Assumptions!$B$28/(1+Assumptions!$B$28),0) -> 0 | E33: =IF(E$4>=$B$46,-(E13+SUM(E16:E22))*Assumptions!$B$28/(1+Assumptions!$B$28),0) -> 0 | F33: =IF(F$4>=$B$46,-(F13+SUM(F16:F22))*Assumptions!$B$28/(1+Assumptions!$B$28),0) -> 0 | G33: =IF(G$4>=$B$46,-(G13+SUM(G16:G22))*Assumptions!$B$28/(1+Assumptions!$B$28),0) -> 0 | H33: =IF(H$4>=$B$46,-(H13+SUM(H16:H22))*Assumptions!$B$28/(1+Assumptions!$B$28),0) -> 0 | I33: =IF(I$4>=$B$46,-(I13+SUM(I16:I22))*Assumptions!$B$28/(1+Assumptions!$B$28),0) -> 0 | J33: =IF(J$4>=$B$46,-(J13+SUM(J16:J22))*Assumptions!$B$28/(1+Assumptions!$B$28),0) -> 0 | ... N33: =IF(N$4>=$B$46,-(N13+SUM(N16:N22))*Assumptions!$B$28/(1+Assumptions!$B$28),0) -> -38702.863
A34: Total overheads and launch | B34: =SUM(C34:N34) -> -191582.86 | C34: =SUM(C30:C33) -> -11230 | D34: =SUM(D30:D33) -> -15150 | E34: =SUM(E30:E33) -> -17150 | F34: =SUM(F30:F33) -> -12150 | G34: =SUM(G30:G33) -> -12150 | H34: =SUM(H30:H33) -> -12150 | I34: =SUM(I30:I33) -> -12150 | J34: =SUM(J30:J33) -> -12150 | ... N34: =SUM(N30:N33) -> -50852.863
A36: Net cash flow | B36: =SUM(C36:N36) -> 1498723.6 | C36: =C27+C34 -> -11230 | D36: =D27+D34 -> 13385.991 | E36: =E27+E34 -> 39921.982 | F36: =F27+F34 -> 59189.978 | G36: =G27+G34 -> 86199.029 | H36: =H27+H34 -> 113208.08 | I36: =I27+I34 -> 140980.6 | J36: =J27+J34 -> 167989.65 | ... N36: =N27+N34 -> 223055
A37: Founder cash injection | B37: =SUM(C37:N37) -> 40000 | C37: =IF(C$4=Assumptions!$B$34,Assumptions!$B$33,0) -> 40000 | D37: =IF(D$4=Assumptions!$B$34,Assumptions!$B$33,0) -> 0 | E37: =IF(E$4=Assumptions!$B$34,Assumptions!$B$33,0) -> 0 | F37: =IF(F$4=Assumptions!$B$34,Assumptions!$B$33,0) -> 0 | G37: =IF(G$4=Assumptions!$B$34,Assumptions!$B$33,0) -> 0 | H37: =IF(H$4=Assumptions!$B$34,Assumptions!$B$33,0) -> 0 | I37: =IF(I$4=Assumptions!$B$34,Assumptions!$B$33,0) -> 0 | J37: =IF(J$4=Assumptions!$B$34,Assumptions!$B$33,0) -> 0 | ... N37: =IF(N$4=Assumptions!$B$34,Assumptions!$B$33,0) -> 0
A38: Opening cash | C38: =0 -> 0 | D38: =C39 -> 28770 | E38: =D39 -> 42155.991 | F38: =E39 -> 82077.973 | G38: =F39 -> 141267.95 | H38: =G39 -> 227466.98 | I38: =H39 -> 340675.06 | J38: =I39 -> 481655.66 | K38: =J39 -> 649645.31 | ... N38: =M39 -> 1315668.6
A39: Closing cash | C39: =C38+C36+C37 -> 28770 | D39: =D38+D36+D37 -> 42155.991 | E39: =E38+E36+E37 -> 82077.973 | F39: =F38+F36+F37 -> 141267.95 | G39: =G38+G36+G37 -> 227466.98 | H39: =H38+H36+H37 -> 340675.06 | I39: =I38+I36+I37 -> 481655.66 | J39: =J38+J36+J37 -> 649645.31 | ... N39: =N38+N36+N37 -> 1538723.6
A41: Checks and helpers
A42: Cumulative net cash flow (before injection) | C42: =C36 -> -11230 | D42: =C42+D36 -> 2155.991 | E42: =D42+E36 -> 42077.973 | F42: =E42+F36 -> 101267.95 | G42: =F42+G36 -> 187466.98 | H42: =G42+H36 -> 300675.06 | I42: =H42+I36 -> 441655.66 | J42: =I42+J36 -> 609645.31 | K42: =J42+K36 -> 804644.01 | ... N42: =M42+N36 -> 1498723.6
A43: Cumulative sales (VAT turnover) | C43: =C10+C11 -> 0 | D43: =C43+D10+D11 -> 50897.4 | E43: =D43+E10+E11 -> 152692.2 | F43: =E43+F10+F11 -> 279935.7 | G43: =F43+G10+G11 -> 458076.6 | H43: =G43+H10+H11 -> 687114.9 | I43: =H43+I10+I11 -> 967050.6 | J43: =I43+J10+J11 -> 1297883.7 | K43: =J43+K10+K11 -> 1679614.2 | ... N43: =M43+N10+N11 -> 3104741.4
A44: Over VAT threshold? (1 = yes) | C44: =IF(C43>Assumptions!$B$29,1,0) -> 0 | D44: =IF(D43>Assumptions!$B$29,1,0) -> 0 | E44: =IF(E43>Assumptions!$B$29,1,0) -> 0 | F44: =IF(F43>Assumptions!$B$29,1,0) -> 0 | G44: =IF(G43>Assumptions!$B$29,1,0) -> 0 | H44: =IF(H43>Assumptions!$B$29,1,0) -> 0 | I44: =IF(I43>Assumptions!$B$29,1,0) -> 0 | J44: =IF(J43>Assumptions!$B$29,1,0) -> 0 | ... N44: =IF(N43>Assumptions!$B$29,1,0) -> 1
A45: Cumulative cash positive? (1 = yes) | C45: =IF(C42>=0,1,0) -> 0 | D45: =IF(D42>=0,1,0) -> 1 | E45: =IF(E42>=0,1,0) -> 1 | F45: =IF(F42>=0,1,0) -> 1 | G45: =IF(G42>=0,1,0) -> 1 | H45: =IF(H42>=0,1,0) -> 1 | I45: =IF(I42>=0,1,0) -> 1 | J45: =IF(J42>=0,1,0) -> 1 | ... N45: =IF(N42>=0,1,0) -> 1
A46: VAT applies from month # | B46: =MIN(Assumptions!B30,IFERROR(MATCH(1,C44:N44,0)+1,13)) -> 12 | C46: Month after cumulative sales pass the threshold, or the voluntary month if earlier. 13 = not in this plan.
A48: Simplifications: refunds for sales in the last 3 months fall after this plan. VAT is paid in the month it arises (SARS works in two-month periods) and only claims input VAT on cost of sales. No income tax is included.
